htmldate/__init__.py
htmldate/cli.py
htmldate/core.py
htmldate/extractors.py
htmldate/meta.py
htmldate/py.typed
htmldate/settings.py
htmldate/utils.py
htmldate/validators.py
htmldate-1.9.2.dist-info/LICENSE
htmldate-1.9.2.dist-info/METADATA
htmldate-1.9.2.dist-info/WHEEL
htmldate-1.9.2.dist-info/entry_points.txt
htmldate-1.9.2.dist-info/top_level.txt
htmldate-1.9.2.dist-info/RECORD
