Metadata-Version: 2.1
Name: htmldate
Version: 1.9.2
Summary: Fast and robust extraction of original and updated publication dates from URLs and web pages.
Author-email: Adrien Barbaresi <barbaresi@bbaw.de>
License: Apache 2.0
Project-URL: Homepage, https://htmldate.readthedocs.io
Project-URL: Source, https://github.com/adbar/htmldate
Project-URL: Blog, https://adrien.barbaresi.eu/blog/
Project-URL: Tracker, https://github.com/adbar/htmldate/issues
Keywords: datetime,date-parser,entity-extraction,html-extraction,html-parsing,metadata-extraction,webarchives,web-scraping
Classifier: Development Status :: 5 - Production/Stable
Classifier: Environment :: Console
Classifier: Intended Audience :: Developers
Classifier: Intended Audience :: Education
Classifier: Intended Audience :: Information Technology
Classifier: Intended Audience :: Science/Research
Classifier: License :: OSI Approved :: Apache Software License
Classifier: Operating System :: MacOS :: MacOS X
Classifier: Operating System :: Microsoft :: Windows
Classifier: Operating System :: POSIX :: Linux
Classifier: Programming Language :: Python
Classifier: Programming Language :: Python :: 3
Classifier: Programming Language :: Python :: 3.8
Classifier: Programming Language :: Python :: 3.9
Classifier: Programming Language :: Python :: 3.10
Classifier: Programming Language :: Python :: 3.11
Classifier: Programming Language :: Python :: 3.12
Classifier: Topic :: Internet :: WWW/HTTP
Classifier: Topic :: Scientific/Engineering :: Information Analysis
Classifier: Topic :: Text Processing :: Linguistic
Classifier: Topic :: Text Processing :: Markup :: HTML
Requires-Python: >=3.8
License-File: LICENSE
Requires-Dist: charset_normalizer>=3.4.0
Requires-Dist: dateparser>=1.1.2
Requires-Dist: lxml==4.9.2; platform_system == "Darwin" and python_version <= "3.8"
Requires-Dist: lxml<6,>=5.3.0; platform_system != "Darwin" or python_version > "3.8"
Requires-Dist: python-dateutil>=2.9.0.post0
Requires-Dist: urllib3<3,>=1.26
Provides-Extra: dev
Requires-Dist: black; extra == "dev"
Requires-Dist: flake8; extra == "dev"
Requires-Dist: mypy; extra == "dev"
Requires-Dist: pytest; extra == "dev"
Requires-Dist: pytest-cov; extra == "dev"
Requires-Dist: types-dateparser; extra == "dev"
Requires-Dist: types-python-dateutil; extra == "dev"
Requires-Dist: types-lxml; extra == "dev"
Requires-Dist: types-urllib3; extra == "dev"
Provides-Extra: speed
Requires-Dist: backports-datetime-fromisoformat; python_version < "3.11" and extra == "speed"
Requires-Dist: faust-cchardet>=2.1.19; extra == "speed"
Requires-Dist: urllib3[brotli]; extra == "speed"
Provides-Extra: all
Requires-Dist: htmldate[dev]; extra == "all"
Requires-Dist: htmldate[speed]; extra == "all"
